{
  "items": [
    {
      "id": "not_1001",
      "title": "Notification 1001",
      "status": "read",
      "createdAt": "2026-01-01T12:00:00.000Z",
      "updatedAt": "2026-01-18T12:00:00.000Z",
      "type": "system",
      "read": true,
      "channel": "email"
    },
    {
      "id": "not_1002",
      "title": "Notification 1002",
      "status": "read",
      "createdAt": "2026-01-01T12:00:00.000Z",
      "updatedAt": "2026-01-18T12:00:00.000Z",
      "type": "system",
      "read": true,
      "channel": "email"
    },
    {
      "id": "not_1003",
      "title": "Notification 1003",
      "status": "read",
      "createdAt": "2026-01-01T12:00:00.000Z",
      "updatedAt": "2026-01-18T12:00:00.000Z",
      "type": "system",
      "read": true,
      "channel": "email"
    }
  ],
  "page": 1,
  "pageSize": 3,
  "total": 3
}
